{
	"caf_01_pingpong.txt": "01",
	"caf_02_count.txt": "03",
	"caf_03_fjthrput.txt": "04",
	"caf_04_fjcreate.txt": "05",
	"caf_05_threadring.txt": "02",
	"caf_06_chameneos.txt": "07",
	"caf_07_big.txt": "08",
	"caf_08_concdict.txt": "09",
	"caf_09_concsll.txt": "10",
	"caf_10_bndbuffer.txt": "11",
	"caf_11_philosopher.txt": "12",
	"caf_14_logmap_become_unbecome_fast.txt": "15.1",
	"caf_14_logmap_become_unbecome_slow.txt": "15.2",
	"caf_14_logmap_request_await_high_timeout.txt": "15.3",
	"caf_14_logmap_request_await_infinite.txt": "15",
	"caf_15_banking_become_unbecome_fast.txt": "16.1",
	"caf_15_banking_become_unbecome_slow.txt": "16.2",
	"caf_15_banking_request_await_high_timeout.txt": "16.3",
	"caf_15_banking_request_await_infinite.txt": "16.4",
	"caf_15_banking_request_then_high_timeout.txt": "16.5",
	"caf_15_banking_request_then_infinite.txt": "16",
	"caf_16_radixsort.txt": "22",
	"caf_18_sieve.txt": "25",
	"caf_20_facloc.txt": "27",
	"caf_21_trapezoid.txt": "28",
	"caf_23_recmatmul.txt": "20",
	"caf_24_quicksort.txt": "21",
	"caf_25_apsp.txt": "17",
	"caf_28_nqueenk.txt": "19",
	"caf_29_fib.txt": "06",
	"caf_30_bitonicsort.txt": "24",
	"ApspAkkaActorBenchmark.txt": "17",
	"BankingAkkaAwaitActorBenchmark.txt": "16.4",
	"BankingAkkaBecomeActorBenchmark.txt": "16.2",
	"BankingAkkaBecomeExtActorBenchmark.txt": "16",
	"BankingAkkaManualStashActorBenchmark.txt": "16.6",
	"BigAkkaActorBenchmark.txt": "08",
	"BitonicSortAkkaActorBenchmark.txt": "24",
	"ChameneosAkkaActorBenchmark.txt": "07",
	"CigaretteSmokerAkkaActorBenchmark.txt": "14",
	"CountingAkkaActorBenchmark.txt": "03",
	"DictionaryAkkaActorBenchmark.txt": "09",
	"FacilityLocationAkkaActorBenchmark.txt": "27",
	"FibonacciAkkaActorBenchmark.txt": "06",
	"FilterBankAkkaActorBenchmark.txt": "23",
	"ForkJoinAkkaActorBenchmark.txt": "05",
	"GuidedSearchAkkaActorBenchmark.txt": "18",
	"GuidedSearchAkkaPriorityActorBenchmark.txt": "18.1",
	"LogisticMapAkkaAwaitActorBenchmark.txt": "15.3",
	"LogisticMapAkkaBecomeActorBenchmark.txt": "15.2",
	"LogisticMapAkkaBecomeExtActorBenchmark.txt": "15",
	"LogisticMapAkkaManualStashActorBenchmark.txt": "15.4",
	"MatMulAkkaActorBenchmark.txt": "20",
	"NQueensAkkaActorBenchmark.txt": "19",
	"NQueensAkkaPriorityActorBenchmark.txt": "19.1",
	"PhilosopherAkkaActorBenchmark.txt": "12",
	"PingPongAkkaActorBenchmark.txt": "01",
	"PiPrecisionAkkaActorBenchmark.txt": "29",
	"ProdConsAkkaActorBenchmark.txt": "11",
	"QuickSortAkkaActorBenchmark.txt": "21",
	"RadixSortAkkaActorBenchmark.txt": "22",
	"SieveAkkaActorBenchmark.txt": "25",
	"SleepingBarberAkkaActorBenchmark.txt": "13",
	"SortedListAkkaActorBenchmark.txt": "10",
	"ThreadRingAkkaActorBenchmark.txt": "02",
	"ThroughputAkkaActorBenchmark.txt": "04",
	"TrapezoidalAkkaActorBenchmark.txt": "28",
	"UctAkkaActorBenchmark.txt": "26",
	"ApspScalaActorBenchmark.txt": "17",
	"BankingScalaActorBenchmark.txt": "16",
	"BigScalaActorBenchmark.txt": "08",
	"BitonicSortScalaActorBenchmark.txt": "24",
	"ChameneosScalaActorBenchmark.txt": "07",
	"CigaretteSmokerScalaActorBenchmark.txt": "14",
	"CountingScalaActorBenchmark.txt": "03",
	"DictionaryScalaActorBenchmark.txt": "09",
	"FacilityLocationScalaActorBenchmark.txt": "27",
	"FibonacciScalaActorBenchmark.txt": "06",
	"FilterBankScalaActorBenchmark.txt": "23",
	"ForkJoinScalaActorBenchmark.txt": "05",
	"GuidedSearchScalaActorBenchmark.txt": "18",
	"LogisticMapScalaActorBenchmark.txt": "15",
	"MatMulScalaActorBenchmark.txt": "20",
	"NQueensScalaActorBenchmark.txt": "19",
	"PhilosopherScalaActorBenchmark.txt": "12",
	"PingPongScalaActorBenchmark.txt": "01",
	"PiPrecisionScalaActorBenchmark.txt": "29",
	"ProdConsScalaActorBenchmark.txt": "11",
	"QuickSortScalaActorBenchmark.txt": "21",
	"RadixSortScalaActorBenchmark.txt": "22",
	"SieveScalaActorBenchmark.txt": "25",
	"SleepingBarberScalaActorBenchmark.txt": "13",
	"SortedListScalaActorBenchmark.txt": "10",
	"ThreadRingScalaActorBenchmark.txt": "02",
	"ThroughputScalaActorBenchmark.txt": "04",
	"TrapezoidalScalaActorBenchmark.txt": "28",
	"UctScalaActorBenchmark.txt": "26",
  "Banking.txt": "16",
  "Barber.txt": "13",
	"Big.txt": "08",
	"BndBuffer.txt": "11",
	"Chameneos.txt": "07",
	"Cigsmok.txt": "14",
  "Concdict.txt": "09",
  "Facloc.txt": "27",
	"Concsll.txt": "10",
	"Count.txt": "03",
  "Fib.txt": "06",
  "Filterbank.txt": "23",
	"Fjcreate.txt": "05",
	"Fjthrput.txt": "04",
	"Logmap.txt": "15",
	"Philosopher.txt": "12",
	"PingPong.txt": "01",
	"Sieve.txt": "25",
  "Threadring.txt": "02",
  "Quicksort.txt": "21",
  "Radixsort.txt": "22",
  "Recmatmul.txt": "20",
	"Trapezoid.txt": "28",
	"benchmarks": {
		"01": "Ping Pong",
		"02": "Thread Ring",
		"03": "Counting Actor",
		"04": "Fork Join (throughput)",
		"05": "Fork Join (actor creation)",
		"06": "Fibonacci",
		"07": "Chameneos",
		"08": "Big",
		"09": "Concurrent Dictionary",
		"10": "Concurrent Sorted Linked-List",
		"11": "Producer-Consumer with Bounded Buffer",
		"12": "Dining Philosophers",
		"13": "Sleeping Barber",
		"14": "Cigarette Smokers",
		"15": "Logistic Map Series (fastest implementations)",
		"15.1": "Logistic Map Series (unbecome fast)",
		"15.2": "Logistic Map Series (unbecome slow)",
		"15.3": "Logistic Map Series (await high timeout)",
		"15.4": "Logistic Map Series (manual stash)", 
		"16": "Bank Transaction (fastest implementations)",
		"16.1": "Bank Transaction (unbecome fast)",
		"16.2": "Bank Transaction (unbecome slow)",
		"16.3": "Bank Transaction (await high timeout)",
		"16.4": "Bank Transaction (await infinite)",
		"16.5": "Bank Transaction (then high timeout)",
		"16.6": "Bank Transaction (manual stash)",
		"17": "All-Pairs Shortest Path",
		"18": "A-Star Search",
		"18.1": "A-Star Search (Priorities)",
		"19": "NQueens first K solutions",
		"19.1": "NQueens first K solutions (Priorities)",
		"20": "Recursive Matrix Multiplication",
		"21": "Quicksort",
		"22": "Radix Sort",
		"23": "Filter Bank",
		"24": "Bitonic Sort",
		"25": "Sieve of Eratosthenes",
		"26": "Unbalanced Cobwebbed Tree",
		"27": "Online Facility Location",
		"28": "Trapezoidal Approximation",
		"29": "Precise Pi Computation",
		"30": "Successive Over-Relaxation"
	},
	"colors": {
	  "Akka": "#FF0000",
	  "CAF": "#0000FF",
	  "Pony": "#00FF00",
	  "Scala": "#551A8B"
	},
	"versions": {
		"Akka": "2.3.2",
		"CAF": "0.16.3",
		"Pony": "0.26.0",
		"Scala": "2.11.0"
	}
}
